{
  "version": 1,
  "snapshots": {
    "vscode:mcp-tool-shop.runforge": {
      "total": 182,
      "fetchedAt": "2026-05-09T08:04:11.116Z"
    },
    "vscode:mcp-tool-shop.codecomfy-vscode": {
      "total": 145,
      "fetchedAt": "2026-05-09T08:04:11.116Z"
    },
    "vscode:mcp-tool-shop.vscode-voice-soundboard": {
      "total": 52,
      "fetchedAt": "2026-05-09T08:04:11.116Z"
    },
    "vscode:mcp-tool-shop.websketch-vscode": {
      "total": 5,
      "fetchedAt": "2026-05-09T08:04:11.116Z"
    },
    "vscode:mcp-tool-shop.polyglot-vscode": {
      "total": 11,
      "fetchedAt": "2026-05-09T08:04:11.116Z"
    },
    "nuget:Attestia.Client": {
      "total": 330,
      "fetchedAt": "2026-05-09T08:04:11.116Z"
    },
    "nuget:Attestia.Core": {
      "total": 372,
      "fetchedAt": "2026-05-09T08:04:11.116Z"
    },
    "nuget:Attestia.Sidecar": {
      "total": 324,
      "fetchedAt": "2026-05-09T08:04:11.116Z"
    },
    "nuget:ClaimLedger": {
      "total": 220,
      "fetchedAt": "2026-05-09T08:04:11.116Z"
    },
    "nuget:CodeClone.Domain": {
      "total": 338,
      "fetchedAt": "2026-05-09T08:04:11.116Z"
    },
    "nuget:CodeTeam": {
      "total": 137,
      "fetchedAt": "2026-05-09T08:04:11.116Z"
    },
    "nuget:CodeTeam.Core": {
      "total": 276,
      "fetchedAt": "2026-05-09T08:04:11.116Z"
    },
    "nuget:CodeTeam.Crypto": {
      "total": 247,
      "fetchedAt": "2026-05-09T08:04:11.116Z"
    },
    "nuget:CodeTeam.Packaging": {
      "total": 205,
      "fetchedAt": "2026-05-09T08:04:11.116Z"
    },
    "nuget:CreatorLedger": {
      "total": 221,
      "fetchedAt": "2026-05-09T08:04:11.116Z"
    },
    "nuget:CursorAssist.Canon": {
      "total": 375,
      "fetchedAt": "2026-05-09T08:04:11.116Z"
    },
    "nuget:CursorAssist.Engine": {
      "total": 333,
      "fetchedAt": "2026-05-09T08:04:11.116Z"
    },
    "nuget:CursorAssist.Policy": {
      "total": 326,
      "fetchedAt": "2026-05-09T08:04:11.116Z"
    },
    "nuget:CursorAssist.Trace": {
      "total": 358,
      "fetchedAt": "2026-05-09T08:04:11.116Z"
    },
    "nuget:DevOpTyper.Content": {
      "total": 429,
      "fetchedAt": "2026-05-09T08:04:11.116Z"
    },
    "nuget:Gov.Common": {
      "total": 354,
      "fetchedAt": "2026-05-09T08:04:11.116Z"
    },
    "nuget:Gov.Protocol": {
      "total": 370,
      "fetchedAt": "2026-05-09T08:04:11.116Z"
    },
    "nuget:InControl.Core": {
      "total": 463,
      "fetchedAt": "2026-05-09T08:04:11.116Z"
    },
    "nuget:InControl.Inference": {
      "total": 224,
      "fetchedAt": "2026-05-09T08:04:11.116Z"
    },
    "nuget:LinuxDevTyper.Core": {
      "total": 433,
      "fetchedAt": "2026-05-09T08:04:11.116Z"
    },
    "nuget:MouseTrainer.Audio": {
      "total": 527,
      "fetchedAt": "2026-05-09T08:04:11.116Z"
    },
    "nuget:MouseTrainer.Domain": {
      "total": 603,
      "fetchedAt": "2026-05-09T08:04:11.116Z"
    },
    "nuget:MouseTrainer.Simulation": {
      "total": 540,
      "fetchedAt": "2026-05-09T08:04:11.116Z"
    },
    "nuget:RunForgeDesktop.Core": {
      "total": 328,
      "fetchedAt": "2026-05-09T08:04:11.116Z"
    },
    "nuget:Soundboard.Client": {
      "total": 367,
      "fetchedAt": "2026-05-09T08:04:11.116Z"
    },
    "nuget:Soundboard.Maui.Audio": {
      "total": 217,
      "fetchedAt": "2026-05-09T08:04:11.116Z"
    },
    "nuget:VortexKit": {
      "total": 236,
      "fetchedAt": "2026-05-09T08:04:11.116Z"
    },
    "vscode:mcp-tool-shop.registry-stats-vscode": {
      "total": 12,
      "fetchedAt": "2026-05-09T08:04:11.116Z"
    }
  }
}
