{
  "version": 1,
  "snapshots": {
    "vscode:mcp-tool-shop.runforge": {
      "total": 311,
      "fetchedAt": "2026-06-05T07:43:22.757Z"
    },
    "vscode:mcp-tool-shop.codecomfy-vscode": {
      "total": 194,
      "fetchedAt": "2026-06-05T07:43:22.757Z"
    },
    "vscode:mcp-tool-shop.vscode-voice-soundboard": {
      "total": 59,
      "fetchedAt": "2026-06-05T07:43:22.757Z"
    },
    "vscode:mcp-tool-shop.websketch-vscode": {
      "total": 5,
      "fetchedAt": "2026-06-05T07:43:22.757Z"
    },
    "vscode:mcp-tool-shop.polyglot-vscode": {
      "total": 11,
      "fetchedAt": "2026-06-05T07:43:22.757Z"
    },
    "nuget:Attestia.Client": {
      "total": 351,
      "fetchedAt": "2026-06-05T07:43:22.757Z"
    },
    "nuget:Attestia.Core": {
      "total": 392,
      "fetchedAt": "2026-06-05T07:43:22.757Z"
    },
    "nuget:Attestia.Sidecar": {
      "total": 343,
      "fetchedAt": "2026-06-05T07:43:22.757Z"
    },
    "nuget:ClaimLedger": {
      "total": 241,
      "fetchedAt": "2026-06-05T07:43:22.757Z"
    },
    "nuget:CodeClone.Domain": {
      "total": 364,
      "fetchedAt": "2026-06-05T07:43:22.757Z"
    },
    "nuget:CodeTeam": {
      "total": 151,
      "fetchedAt": "2026-06-05T07:43:22.757Z"
    },
    "nuget:CodeTeam.Core": {
      "total": 293,
      "fetchedAt": "2026-06-05T07:43:22.757Z"
    },
    "nuget:CodeTeam.Crypto": {
      "total": 267,
      "fetchedAt": "2026-06-05T07:43:22.757Z"
    },
    "nuget:CodeTeam.Packaging": {
      "total": 223,
      "fetchedAt": "2026-06-05T07:43:22.757Z"
    },
    "nuget:CreatorLedger": {
      "total": 250,
      "fetchedAt": "2026-06-05T07:43:22.757Z"
    },
    "nuget:CursorAssist.Canon": {
      "total": 403,
      "fetchedAt": "2026-06-05T07:43:22.757Z"
    },
    "nuget:CursorAssist.Engine": {
      "total": 357,
      "fetchedAt": "2026-06-05T07:43:22.757Z"
    },
    "nuget:CursorAssist.Policy": {
      "total": 353,
      "fetchedAt": "2026-06-05T07:43:22.757Z"
    },
    "nuget:CursorAssist.Trace": {
      "total": 389,
      "fetchedAt": "2026-06-05T07:43:22.757Z"
    },
    "nuget:DevOpTyper.Content": {
      "total": 468,
      "fetchedAt": "2026-06-05T07:43:22.757Z"
    },
    "nuget:Gov.Common": {
      "total": 386,
      "fetchedAt": "2026-06-05T07:43:22.757Z"
    },
    "nuget:Gov.Protocol": {
      "total": 389,
      "fetchedAt": "2026-06-05T07:43:22.757Z"
    },
    "nuget:InControl.Core": {
      "total": 496,
      "fetchedAt": "2026-06-05T07:43:22.757Z"
    },
    "nuget:InControl.Inference": {
      "total": 243,
      "fetchedAt": "2026-06-05T07:43:22.757Z"
    },
    "nuget:LinuxDevTyper.Core": {
      "total": 469,
      "fetchedAt": "2026-06-05T07:43:22.757Z"
    },
    "nuget:MouseTrainer.Audio": {
      "total": 576,
      "fetchedAt": "2026-06-05T07:43:22.757Z"
    },
    "nuget:MouseTrainer.Domain": {
      "total": 654,
      "fetchedAt": "2026-06-05T07:43:22.757Z"
    },
    "nuget:MouseTrainer.Simulation": {
      "total": 592,
      "fetchedAt": "2026-06-05T07:43:22.757Z"
    },
    "nuget:RunForgeDesktop.Core": {
      "total": 357,
      "fetchedAt": "2026-06-05T07:43:22.757Z"
    },
    "nuget:Soundboard.Client": {
      "total": 404,
      "fetchedAt": "2026-06-05T07:43:22.757Z"
    },
    "nuget:Soundboard.Maui.Audio": {
      "total": 235,
      "fetchedAt": "2026-06-05T07:43:22.757Z"
    },
    "nuget:VortexKit": {
      "total": 250,
      "fetchedAt": "2026-06-05T07:43:22.757Z"
    },
    "vscode:mcp-tool-shop.registry-stats-vscode": {
      "total": 12,
      "fetchedAt": "2026-06-05T07:43:22.757Z"
    }
  }
}
